__init__.py
chronotva/__init__.py
chronotva/cli.py
chronotva/default_data.py
chronotva/tesseract.py
chronotva-1.0.1.dist-info/LICENSE
chronotva-1.0.1.dist-info/METADATA
chronotva-1.0.1.dist-info/WHEEL
chronotva-1.0.1.dist-info/entry_points.txt
chronotva-1.0.1.dist-info/top_level.txt
chronotva-1.0.1.dist-info/RECORD
