Metadata-Version: 2.1
Name: chronotva
Version: 1.0.1
Summary: ChronoTVA (The Chronomancer's Tesseract Visualization Aid) is a Python 3.9+ command-line tool designed for generating images from three-dimensional coordinates of all possible unfoldings of a tesseract (hypercube).
Author-email: Jacob Coleman <jacob.wade.coleman@gmail.com>
Project-URL: Homepage, https://github.com/the-chronomancer/chronotva
Project-URL: Documentation, https://github.com/the-chronomancer/chronotva/README.md
Project-URL: Source, https://github.com/the-chronomancer/chronotva
Project-URL: Tracker, https://github.com/the-chronomancer/chronotva/issues
Keywords: tesseract,visualization,aid,unfoldings,isomorphism,matplotlib,oop
Classifier: Development Status :: 5 - Production/Stable
Classifier: Intended Audience :: Developers
Classifier: License :: OSI Approved :: MIT License
Classifier: Programming Language :: Python :: 3
Classifier: Programming Language :: Python :: 3.9
Classifier: Programming Language :: Python :: 3.10
Classifier: Programming Language :: Python :: 3.11
Classifier: Programming Language :: Python :: 3.12
Requires-Python: >=3.9
License-File: LICENSE
Requires-Dist: matplotlib
Provides-Extra: dev
Requires-Dist: pytest >=6.0.0 ; extra == 'dev'
Requires-Dist: mypy >=0.800 ; extra == 'dev'
Requires-Dist: isort >=5.0.0 ; extra == 'dev'
Requires-Dist: black >=20.8b1 ; extra == 'dev'
